target_miso/__init__.py
target_miso/extensions.py
target_miso/miso.py
target_miso/py_extensions.py
target_miso/target.py
target_miso-0.9.5.dist-info/LICENSE
target_miso-0.9.5.dist-info/METADATA
target_miso-0.9.5.dist-info/WHEEL
target_miso-0.9.5.dist-info/entry_points.txt
target_miso-0.9.5.dist-info/top_level.txt
target_miso-0.9.5.dist-info/RECORD
