Metadata-Version: 2.1
Name: target-miso
Version: 0.9.5
Summary: A Singer target for writing data to Miso API
Home-page: https://github.com/MisoAI/target-miso
Author: Hash Lin
Author-email: hashlin@askmiso.com
License: MIT
Keywords: singer,singer.io,target,ETL,ELT,MisoAI,Miso,Meltano
Classifier: Programming Language :: Python :: 3 :: Only
Classifier: License :: OSI Approved :: MIT License
Classifier: Operating System :: OS Independent
License-File: LICENSE
Requires-Dist: singer-python
Requires-Dist: requests
Requires-Dist: jsonnet
Requires-Dist: sentry-sdk
Requires-Dist: simplejson
Requires-Dist: dateparser
Requires-Dist: Jinja2
